geometrie.py
geometrie-0.0.1.dist-info/LICENSE
geometrie-0.0.1.dist-info/METADATA
geometrie-0.0.1.dist-info/WHEEL
geometrie-0.0.1.dist-info/top_level.txt
geometrie-0.0.1.dist-info/RECORD
